Workbook

Sheet Help
A1: Interactive Period Filter (Summary!K1): Selecting All Year (2025) aggregates the entire year's operations across January and February. Choosing any individual month (such as January or February) instantly filters all KPI metrics, agent distributions, and expense breakdowns to that specific month. Months without data cleanly display zero values with zero calculation errors.
A2: Executive Summary Cards (Summary!B2:K6):
A3: Total Invoiced: Total client billing for the selected period (PKR 1,518,900 full year / PKR 852,900 February).
A4: Total Collections: Cash and online payments collected (PKR 1,323,900 full year / PKR 852,900 February).
A5: Balance Receivable: Remaining unpaid customer invoices (PKR 195,000 full year / PKR 0 February).
A6: Vendor Payables: Direct cost of visas, appointments, and supplier expenses (PKR 807,672 full year / PKR 494,047 February).
A7: Operating Expenses: Office running overheads (PKR 115,290 full year / PKR 35,890 February).
A8: Gross Profit: Total invoiced revenue minus direct vendor costs (PKR 711,228 full year / PKR 358,853 February).
A9: Net Operating Profit: Gross profit minus overhead expenses (PKR 595,938 full year / PKR 322,963 February).
A10: Net Cash Position: Collections minus vendor payouts and operating expenses (PKR 400,938 full year / PKR 322,963 February).
A11: Master Sales Ledger (Sales!A13:M28): Added 16 February customer transactions with automated formulas calculating receivable balances and gross profit per transaction, followed by an updated full-ledger total row.
A12: Master Expenses Ledger (Expenses!A13:G22): Added 10 February operating expenses with standardized categories, paid-to entities, and payment methods, followed by an updated total row.
A13: Monthly Tab Preservation: All original monthly tabs (including February, March, April, etc.) remain 100% unaltered so your staff can audit and reconcile every figure against original notes.

Sheet Summary
B1: KAMAL EXPRESS • EXECUTIVE FINANCIAL DASHBOARD | J1: Filter Month: | K1: Year 2026
B2: TOTAL INVOICED | D2: TOTAL COLLECTIONS | F2: BALANCE RECEIVABLE | H2: VENDOR PAYABLES | J2: OPERATING EXPENSES
B3: {=SUMIFS(Sales!$H$2:$H$500, Sales!$B$2:$B$500, ">="&IF(ISNUMBER($K$1),DATE(YEAR($K$1),MONTH($K$1),1),IF(ISNUMBER(SEARCH("2025",$K$1)),DATE(2025,1,1),IF(ISNUMBER(SEARCH("2026",$K$1)),DATE(2026,1,1),IF(ISNUMBER(MATCH($K$1,{"January","February","March","April","May","June","July","August","September","October","November","December"},0)),DATE(2025,MATCH($K$1,{"January","February","March","April","May","June","July","August","September","October","November","December"},0),1),DATE(2020,1,1))))), Sales!$B$2:$B$500, "<="&IF(ISNUMBER($K$1),EOMONTH($K$1,0),IF(ISNUMBER(SEARCH("2025",$K$1)),DATE(2025,12,31),IF(ISNUMBER(SEARCH("2026",$K$1)),DATE(2026,12,31),IF(ISNUMBER(MATCH($K$1,{"January","February","March","April","May","June","July","August","September","October","November","December"},0)),EOMONTH(DATE(2025,MATCH($K$1,{"January","February","March","April","May","June","July","August","September","October","November","December"},0),1),0),DATE(2030,12,31))))))} -> 8782108 | D3: {=SUMIFS(Sales!$I$2:$I$500, Sales!$B$2:$B$500, ">="&IF(ISNUMBER($K$1),DATE(YEAR($K$1),MONTH($K$1),1),IF(ISNUMBER(SEARCH("2025",$K$1)),DATE(2025,1,1),IF(ISNUMBER(SEARCH("2026",$K$1)),DATE(2026,1,1),IF(ISNUMBER(MATCH($K$1,{"January","February","March","April","May","June","July","August","September","October","November","December"},0)),DATE(2025,MATCH($K$1,{"January","February","March","April","May","June","July","August","September","October","November","December"},0),1),DATE(2020,1,1))))), Sales!$B$2:$B$500, "<="&IF(ISNUMBER($K$1),EOMONTH($K$1,0),IF(ISNUMBER(SEARCH("2025",$K$1)),DATE(2025,12,31),IF(ISNUMBER(SEARCH("2026",$K$1)),DATE(2026,12,31),IF(ISNUMBER(MATCH($K$1,{"January","February","March","April","May","June","July","August","September","October","November","December"},0)),EOMONTH(DATE(2025,MATCH($K$1,{"January","February","March","April","May","June","July","August","September","October","November","December"},0),1),0),DATE(2030,12,31))))))} -> 8505100 | F3: {=SUMIFS(Sales!$J$2:$J$500, Sales!$B$2:$B$500, ">="&IF(ISNUMBER($K$1),DATE(YEAR($K$1),MONTH($K$1),1),IF(ISNUMBER(SEARCH("2025",$K$1)),DATE(2025,1,1),IF(ISNUMBER(SEARCH("2026",$K$1)),DATE(2026,1,1),IF(ISNUMBER(MATCH($K$1,{"January","February","March","April","May","June","July","August","September","October","November","December"},0)),DATE(2025,MATCH($K$1,{"January","February","March","April","May","June","July","August","September","October","November","December"},0),1),DATE(2020,1,1))))), Sales!$B$2:$B$500, "<="&IF(ISNUMBER($K$1),EOMONTH($K$1,0),IF(ISNUMBER(SEARCH("2025",$K$1)),DATE(2025,12,31),IF(ISNUMBER(SEARCH("2026",$K$1)),DATE(2026,12,31),IF(ISNUMBER(MATCH($K$1,{"January","February","March","April","May","June","July","August","September","October","November","December"},0)),EOMONTH(DATE(2025,MATCH($K$1,{"January","February","March","April","May","June","July","August","September","October","November","December"},0),1),0),DATE(2030,12,31))))))} -> 277008 | H3: {=SUMIFS(Sales!$K$2:$K$500, Sales!$B$2:$B$500, ">="&IF(ISNUMBER($K$1),DATE(YEAR($K$1),MONTH($K$1),1),IF(ISNUMBER(SEARCH("2025",$K$1)),DATE(2025,1,1),IF(ISNUMBER(SEARCH("2026",$K$1)),DATE(2026,1,1),IF(ISNUMBER(MATCH($K$1,{"January","February","March","April","May","June","July","August","September","October","November","December"},0)),DATE(2025,MATCH($K$1,{"January","February","March","April","May","June","July","August","September","October","November","December"},0),1),DATE(2020,1,1))))), Sales!$B$2:$B$500, "<="&IF(ISNUMBER($K$1),EOMONTH($K$1,0),IF(ISNUMBER(SEARCH("2025",$K$1)),DATE(2025,12,31),IF(ISNUMBER(SEARCH("2026",$K$1)),DATE(2026,12,31),IF(ISNUMBER(MATCH($K$1,{"January","February","March","April","May","June","July","August","September","October","November","December"},0)),EOMONTH(DATE(2025,MATCH($K$1,{"January","February","March","April","May","June","July","August","September","October","November","December"},0),1),0),DATE(2030,12,31))))))} -> 2242098 | J3: {=SUMIFS(Expenses!$D$2:$D$500, Expenses!$A$2:$A$500, ">="&IF(ISNUMBER($K$1),DATE(YEAR($K$1),MONTH($K$1),1),IF(ISNUMBER(SEARCH("2025",$K$1)),DATE(2025,1,1),IF(ISNUMBER(SEARCH("2026",$K$1)),DATE(2026,1,1),IF(ISNUMBER(MATCH($K$1,{"January","February","March","April","May","June","July","August","September","October","November","December"},0)),DATE(2025,MATCH($K$1,{"January","February","March","April","May","June","July","August","September","October","November","December"},0),1),DATE(2020,1,1))))), Expenses!$A$2:$A$500, "<="&IF(ISNUMBER($K$1),EOMONTH($K$1,0),IF(ISNUMBER(SEARCH("2025",$K$1)),DATE(2025,12,31),IF(ISNUMBER(SEARCH("2026",$K$1)),DATE(2026,12,31),IF(ISNUMBER(MATCH($K$1,{"January","February","March","April","May","June","July","August","September","October","November","December"},0)),EOMONTH(DATE(2025,MATCH($K$1,{"January","February","March","April","May","June","July","August","September","October","November","December"},0),1),0),DATE(2030,12,31))))))} -> 373948
B5: GROSS PROFIT | E5: NET OPERATING PROFIT | H5: NET CASH POSITION
B6: {=SUMIFS(Sales!$M$2:$M$500, Sales!$B$2:$B$500, ">="&IF(ISNUMBER($K$1),DATE(YEAR($K$1),MONTH($K$1),1),IF(ISNUMBER(SEARCH("2025",$K$1)),DATE(2025,1,1),IF(ISNUMBER(SEARCH("2026",$K$1)),DATE(2026,1,1),IF(ISNUMBER(MATCH($K$1,{"January","February","March","April","May","June","July","August","September","October","November","December"},0)),DATE(2025,MATCH($K$1,{"January","February","March","April","May","June","July","August","September","October","November","December"},0),1),DATE(2020,1,1))))), Sales!$B$2:$B$500, "<="&IF(ISNUMBER($K$1),EOMONTH($K$1,0),IF(ISNUMBER(SEARCH("2025",$K$1)),DATE(2025,12,31),IF(ISNUMBER(SEARCH("2026",$K$1)),DATE(2026,12,31),IF(ISNUMBER(MATCH($K$1,{"January","February","March","April","May","June","July","August","September","October","November","December"},0)),EOMONTH(DATE(2025,MATCH($K$1,{"January","February","March","April","May","June","July","August","September","October","November","December"},0),1),0),DATE(2030,12,31))))))} -> 6540010 | E6: =B6-J3 -> 6166062 | H6: =D3-H3-J3 -> 5889054
B8: Agent (Care Of) | C8: Total Invoiced | D8: Collected | E8: Receivable | F8: Gross Profit | H8: Expense Category | I8: Total Spent | J8: % of Total | K8: Tx Count
B9: Kamal | C9: {=SUMIFS(Sales!$H$2:$H$500, Sales!$D$2:$D$500, $B9, Sales!$B$2:$B$500, ">="&IF(ISNUMBER($K$1),DATE(YEAR($K$1),MONTH($K$1),1),IF(ISNUMBER(SEARCH("2025",$K$1)),DATE(2025,1,1),IF(ISNUMBER(SEARCH("2026",$K$1)),DATE(2026,1,1),IF(ISNUMBER(MATCH($K$1,{"January","February","March","April","May","June","July","August","September","October","November","December"},0)),DATE(2025,MATCH($K$1,{"January","February","March","April","May","June","July","August","September","October","November","December"},0),1),DATE(2020,1,1))))), Sales!$B$2:$B$500, "<="&IF(ISNUMBER($K$1),EOMONTH($K$1,0),IF(ISNUMBER(SEARCH("2025",$K$1)),DATE(2025,12,31),IF(ISNUMBER(SEARCH("2026",$K$1)),DATE(2026,12,31),IF(ISNUMBER(MATCH($K$1,{"January","February","March","April","May","June","July","August","September","October","November","December"},0)),EOMONTH(DATE(2025,MATCH($K$1,{"January","February","March","April","May","June","July","August","September","October","November","December"},0),1),0),DATE(2030,12,31))))))} -> 1682408 | D9: {=SUMIFS(Sales!$I$2:$I$500, Sales!$D$2:$D$500, $B9, Sales!$B$2:$B$500, ">="&IF(ISNUMBER($K$1),DATE(YEAR($K$1),MONTH($K$1),1),IF(ISNUMBER(SEARCH("2025",$K$1)),DATE(2025,1,1),IF(ISNUMBER(SEARCH("2026",$K$1)),DATE(2026,1,1),IF(ISNUMBER(MATCH($K$1,{"January","February","March","April","May","June","July","August","September","October","November","December"},0)),DATE(2025,MATCH($K$1,{"January","February","March","April","May","June","July","August","September","October","November","December"},0),1),DATE(2020,1,1))))), Sales!$B$2:$B$500, "<="&IF(ISNUMBER($K$1),EOMONTH($K$1,0),IF(ISNUMBER(SEARCH("2025",$K$1)),DATE(2025,12,31),IF(ISNUMBER(SEARCH("2026",$K$1)),DATE(2026,12,31),IF(ISNUMBER(MATCH($K$1,{"January","February","March","April","May","June","July","August","September","October","November","December"},0)),EOMONTH(DATE(2025,MATCH($K$1,{"January","February","March","April","May","June","July","August","September","October","November","December"},0),1),0),DATE(2030,12,31))))))} -> 1469700 | E9: {=SUMIFS(Sales!$J$2:$J$500, Sales!$D$2:$D$500, $B9, Sales!$B$2:$B$500, ">="&IF(ISNUMBER($K$1),DATE(YEAR($K$1),MONTH($K$1),1),IF(ISNUMBER(SEARCH("2025",$K$1)),DATE(2025,1,1),IF(ISNUMBER(SEARCH("2026",$K$1)),DATE(2026,1,1),IF(ISNUMBER(MATCH($K$1,{"January","February","March","April","May","June","July","August","September","October","November","December"},0)),DATE(2025,MATCH($K$1,{"January","February","March","April","May","June","July","August","September","October","November","December"},0),1),DATE(2020,1,1))))), Sales!$B$2:$B$500, "<="&IF(ISNUMBER($K$1),EOMONTH($K$1,0),IF(ISNUMBER(SEARCH("2025",$K$1)),DATE(2025,12,31),IF(ISNUMBER(SEARCH("2026",$K$1)),DATE(2026,12,31),IF(ISNUMBER(MATCH($K$1,{"January","February","March","April","May","June","July","August","September","October","November","December"},0)),EOMONTH(DATE(2025,MATCH($K$1,{"January","February","March","April","May","June","July","August","September","October","November","December"},0),1),0),DATE(2030,12,31))))))} -> 212708 | F9: {=SUMIFS(Sales!$M$2:$M$500, Sales!$D$2:$D$500, $B9, Sales!$B$2:$B$500, ">="&IF(ISNUMBER($K$1),DATE(YEAR($K$1),MONTH($K$1),1),IF(ISNUMBER(SEARCH("2025",$K$1)),DATE(2025,1,1),IF(ISNUMBER(SEARCH("2026",$K$1)),DATE(2026,1,1),IF(ISNUMBER(MATCH($K$1,{"January","February","March","April","May","June","July","August","September","October","November","December"},0)),DATE(2025,MATCH($K$1,{"January","February","March","April","May","June","July","August","September","October","November","December"},0),1),DATE(2020,1,1))))), Sales!$B$2:$B$500, "<="&IF(ISNUMBER($K$1),EOMONTH($K$1,0),IF(ISNUMBER(SEARCH("2025",$K$1)),DATE(2025,12,31),IF(ISNUMBER(SEARCH("2026",$K$1)),DATE(2026,12,31),IF(ISNUMBER(MATCH($K$1,{"January","February","March","April","May","June","July","August","September","October","November","December"},0)),EOMONTH(DATE(2025,MATCH($K$1,{"January","February","March","April","May","June","July","August","September","October","November","December"},0),1),0),DATE(2030,12,31))))))} -> 845508 | H9: Utilities | I9: {=SUMIFS(Expenses!$D$2:$D$500, Expenses!$B$2:$B$500, $H9, Expenses!$A$2:$A$500, ">="&IF(ISNUMBER($K$1),DATE(YEAR($K$1),MONTH($K$1),1),IF(ISNUMBER(SEARCH("2025",$K$1)),DATE(2025,1,1),IF(ISNUMBER(SEARCH("2026",$K$1)),DATE(2026,1,1),IF(ISNUMBER(MATCH($K$1,{"January","February","March","April","May","June","July","August","September","October","November","December"},0)),DATE(2025,MATCH($K$1,{"January","February","March","April","May","June","July","August","September","October","November","December"},0),1),DATE(2020,1,1))))), Expenses!$A$2:$A$500, "<="&IF(ISNUMBER($K$1),EOMONTH($K$1,0),IF(ISNUMBER(SEARCH("2025",$K$1)),DATE(2025,12,31),IF(ISNUMBER(SEARCH("2026",$K$1)),DATE(2026,12,31),IF(ISNUMBER(MATCH($K$1,{"January","February","March","April","May","June","July","August","September","October","November","December"},0)),EOMONTH(DATE(2025,MATCH($K$1,{"January","February","March","April","May","June","July","August","September","October","November","December"},0),1),0),DATE(2030,12,31))))))} -> 126508 | J9: =IFERROR(I9/$I$15,0) -> 0.33830372 | K9: {=COUNTIFS(Expenses!$B$2:$B$500, $H9, Expenses!$A$2:$A$500, ">="&IF(ISNUMBER($K$1),DATE(YEAR($K$1),MONTH($K$1),1),IF(ISNUMBER(SEARCH("2025",$K$1)),DATE(2025,1,1),IF(ISNUMBER(SEARCH("2026",$K$1)),DATE(2026,1,1),IF(ISNUMBER(MATCH($K$1,{"January","February","March","April","May","June","July","August","September","October","November","December"},0)),DATE(2025,MATCH($K$1,{"January","February","March","April","May","June","July","August","September","October","November","December"},0),1),DATE(2020,1,1))))), Expenses!$A$2:$A$500, "<="&IF(ISNUMBER($K$1),EOMONTH($K$1,0),IF(ISNUMBER(SEARCH("2025",$K$1)),DATE(2025,12,31),IF(ISNUMBER(SEARCH("2026",$K$1)),DATE(2026,12,31),IF(ISNUMBER(MATCH($K$1,{"January","February","March","April","May","June","July","August","September","October","November","December"},0)),EOMONTH(DATE(2025,MATCH($K$1,{"January","February","March","April","May","June","July","August","September","October","November","December"},0),1),0),DATE(2030,12,31))))))} -> 20
B10: Zeeshan | C10: {=SUMIFS(Sales!$H$2:$H$500, Sales!$D$2:$D$500, $B10, Sales!$B$2:$B$500, ">="&IF(ISNUMBER($K$1),DATE(YEAR($K$1),MONTH($K$1),1),IF(ISNUMBER(SEARCH("2025",$K$1)),DATE(2025,1,1),IF(ISNUMBER(SEARCH("2026",$K$1)),DATE(2026,1,1),IF(ISNUMBER(MATCH($K$1,{"January","February","March","April","May","June","July","August","September","October","November","December"},0)),DATE(2025,MATCH($K$1,{"January","February","March","April","May","June","July","August","September","October","November","December"},0),1),DATE(2020,1,1))))), Sales!$B$2:$B$500, "<="&IF(ISNUMBER($K$1),EOMONTH($K$1,0),IF(ISNUMBER(SEARCH("2025",$K$1)),DATE(2025,12,31),IF(ISNUMBER(SEARCH("2026",$K$1)),DATE(2026,12,31),IF(ISNUMBER(MATCH($K$1,{"January","February","March","April","May","June","July","August","September","October","November","December"},0)),EOMONTH(DATE(2025,MATCH($K$1,{"January","February","March","April","May","June","July","August","September","October","November","December"},0),1),0),DATE(2030,12,31))))))} -> 6684700 | D10: {=SUMIFS(Sales!$I$2:$I$500, Sales!$D$2:$D$500, $B10, Sales!$B$2:$B$500, ">="&IF(ISNUMBER($K$1),DATE(YEAR($K$1),MONTH($K$1),1),IF(ISNUMBER(SEARCH("2025",$K$1)),DATE(2025,1,1),IF(ISNUMBER(SEARCH("2026",$K$1)),DATE(2026,1,1),IF(ISNUMBER(MATCH($K$1,{"January","February","March","April","May","June","July","August","September","October","November","December"},0)),DATE(2025,MATCH($K$1,{"January","February","March","April","May","June","July","August","September","October","November","December"},0),1),DATE(2020,1,1))))), Sales!$B$2:$B$500, "<="&IF(ISNUMBER($K$1),EOMONTH($K$1,0),IF(ISNUMBER(SEARCH("2025",$K$1)),DATE(2025,12,31),IF(ISNUMBER(SEARCH("2026",$K$1)),DATE(2026,12,31),IF(ISNUMBER(MATCH($K$1,{"January","February","March","April","May","June","July","August","September","October","November","December"},0)),EOMONTH(DATE(2025,MATCH($K$1,{"January","February","March","April","May","June","July","August","September","October","November","December"},0),1),0),DATE(2030,12,31))))))} -> 6620400 | E10: {=SUMIFS(Sales!$J$2:$J$500, Sales!$D$2:$D$500, $B10, Sales!$B$2:$B$500, ">="&IF(ISNUMBER($K$1),DATE(YEAR($K$1),MONTH($K$1),1),IF(ISNUMBER(SEARCH("2025",$K$1)),DATE(2025,1,1),IF(ISNUMBER(SEARCH("2026",$K$1)),DATE(2026,1,1),IF(ISNUMBER(MATCH($K$1,{"January","February","March","April","May","June","July","August","September","October","November","December"},0)),DATE(2025,MATCH($K$1,{"January","February","March","April","May","June","July","August","September","October","November","December"},0),1),DATE(2020,1,1))))), Sales!$B$2:$B$500, "<="&IF(ISNUMBER($K$1),EOMONTH($K$1,0),IF(ISNUMBER(SEARCH("2025",$K$1)),DATE(2025,12,31),IF(ISNUMBER(SEARCH("2026",$K$1)),DATE(2026,12,31),IF(ISNUMBER(MATCH($K$1,{"January","February","March","April","May","June","July","August","September","October","November","December"},0)),EOMONTH(DATE(2025,MATCH($K$1,{"January","February","March","April","May","June","July","August","September","October","November","December"},0),1),0),DATE(2030,12,31))))))} -> 64300 | F10: {=SUMIFS(Sales!$M$2:$M$500, Sales!$D$2:$D$500, $B10, Sales!$B$2:$B$500, ">="&IF(ISNUMBER($K$1),DATE(YEAR($K$1),MONTH($K$1),1),IF(ISNUMBER(SEARCH("2025",$K$1)),DATE(2025,1,1),IF(ISNUMBER(SEARCH("2026",$K$1)),DATE(2026,1,1),IF(ISNUMBER(MATCH($K$1,{"January","February","March","April","May","June","July","August","September","October","November","December"},0)),DATE(2025,MATCH($K$1,{"January","February","March","April","May","June","July","August","September","October","November","December"},0),1),DATE(2020,1,1))))), Sales!$B$2:$B$500, "<="&IF(ISNUMBER($K$1),EOMONTH($K$1,0),IF(ISNUMBER(SEARCH("2025",$K$1)),DATE(2025,12,31),IF(ISNUMBER(SEARCH("2026",$K$1)),DATE(2026,12,31),IF(ISNUMBER(MATCH($K$1,{"January","February","March","April","May","June","July","August","September","October","November","December"},0)),EOMONTH(DATE(2025,MATCH($K$1,{"January","February","March","April","May","June","July","August","September","October","November","December"},0),1),0),DATE(2030,12,31))))))} -> 5323502 | H10: Salaries & Wages | I10: {=SUMIFS(Expenses!$D$2:$D$500, Expenses!$B$2:$B$500, $H10, Expenses!$A$2:$A$500, ">="&IF(ISNUMBER($K$1),DATE(YEAR($K$1),MONTH($K$1),1),IF(ISNUMBER(SEARCH("2025",$K$1)),DATE(2025,1,1),IF(ISNUMBER(SEARCH("2026",$K$1)),DATE(2026,1,1),IF(ISNUMBER(MATCH($K$1,{"January","February","March","April","May","June","July","August","September","October","November","December"},0)),DATE(2025,MATCH($K$1,{"January","February","March","April","May","June","July","August","September","October","November","December"},0),1),DATE(2020,1,1))))), Expenses!$A$2:$A$500, "<="&IF(ISNUMBER($K$1),EOMONTH($K$1,0),IF(ISNUMBER(SEARCH("2025",$K$1)),DATE(2025,12,31),IF(ISNUMBER(SEARCH("2026",$K$1)),DATE(2026,12,31),IF(ISNUMBER(MATCH($K$1,{"January","February","March","April","May","June","July","August","September","October","November","December"},0)),EOMONTH(DATE(2025,MATCH($K$1,{"January","February","March","April","May","June","July","August","September","October","November","December"},0),1),0),DATE(2030,12,31))))))} -> 80000 | J10: =IFERROR(I10/$I$15,0) -> 0.21393349 | K10: {=COUNTIFS(Expenses!$B$2:$B$500, $H10, Expenses!$A$2:$A$500, ">="&IF(ISNUMBER($K$1),DATE(YEAR($K$1),MONTH($K$1),1),IF(ISNUMBER(SEARCH("2025",$K$1)),DATE(2025,1,1),IF(ISNUMBER(SEARCH("2026",$K$1)),DATE(2026,1,1),IF(ISNUMBER(MATCH($K$1,{"January","February","March","April","May","June","July","August","September","October","November","December"},0)),DATE(2025,MATCH($K$1,{"January","February","March","April","May","June","July","August","September","October","November","December"},0),1),DATE(2020,1,1))))), Expenses!$A$2:$A$500, "<="&IF(ISNUMBER($K$1),EOMONTH($K$1,0),IF(ISNUMBER(SEARCH("2025",$K$1)),DATE(2025,12,31),IF(ISNUMBER(SEARCH("2026",$K$1)),DATE(2026,12,31),IF(ISNUMBER(MATCH($K$1,{"January","February","March","April","May","June","July","August","September","October","November","December"},0)),EOMONTH(DATE(2025,MATCH($K$1,{"January","February","March","April","May","June","July","August","September","October","November","December"},0),1),0),DATE(2030,12,31))))))} -> 4
B11: Company | C11: {=SUMIFS(Sales!$H$2:$H$500, Sales!$D$2:$D$500, $B11, Sales!$B$2:$B$500, ">="&IF(ISNUMBER($K$1),DATE(YEAR($K$1),MONTH($K$1),1),IF(ISNUMBER(SEARCH("2025",$K$1)),DATE(2025,1,1),IF(ISNUMBER(SEARCH("2026",$K$1)),DATE(2026,1,1),IF(ISNUMBER(MATCH($K$1,{"January","February","March","April","May","June","July","August","September","October","November","December"},0)),DATE(2025,MATCH($K$1,{"January","February","March","April","May","June","July","August","September","October","November","December"},0),1),DATE(2020,1,1))))), Sales!$B$2:$B$500, "<="&IF(ISNUMBER($K$1),EOMONTH($K$1,0),IF(ISNUMBER(SEARCH("2025",$K$1)),DATE(2025,12,31),IF(ISNUMBER(SEARCH("2026",$K$1)),DATE(2026,12,31),IF(ISNUMBER(MATCH($K$1,{"January","February","March","April","May","June","July","August","September","October","November","December"},0)),EOMONTH(DATE(2025,MATCH($K$1,{"January","February","March","April","May","June","July","August","September","October","November","December"},0),1),0),DATE(2030,12,31))))))} -> 65000 | D11: {=SUMIFS(Sales!$I$2:$I$500, Sales!$D$2:$D$500, $B11, Sales!$B$2:$B$500, ">="&IF(ISNUMBER($K$1),DATE(YEAR($K$1),MONTH($K$1),1),IF(ISNUMBER(SEARCH("2025",$K$1)),DATE(2025,1,1),IF(ISNUMBER(SEARCH("2026",$K$1)),DATE(2026,1,1),IF(ISNUMBER(MATCH($K$1,{"January","February","March","April","May","June","July","August","September","October","November","December"},0)),DATE(2025,MATCH($K$1,{"January","February","March","April","May","June","July","August","September","October","November","December"},0),1),DATE(2020,1,1))))), Sales!$B$2:$B$500, "<="&IF(ISNUMBER($K$1),EOMONTH($K$1,0),IF(ISNUMBER(SEARCH("2025",$K$1)),DATE(2025,12,31),IF(ISNUMBER(SEARCH("2026",$K$1)),DATE(2026,12,31),IF(ISNUMBER(MATCH($K$1,{"January","February","March","April","May","June","July","August","September","October","November","December"},0)),EOMONTH(DATE(2025,MATCH($K$1,{"January","February","March","April","May","June","July","August","September","October","November","December"},0),1),0),DATE(2030,12,31))))))} -> 65000 | E11: {=SUMIFS(Sales!$J$2:$J$500, Sales!$D$2:$D$500, $B11, Sales!$B$2:$B$500, ">="&IF(ISNUMBER($K$1),DATE(YEAR($K$1),MONTH($K$1),1),IF(ISNUMBER(SEARCH("2025",$K$1)),DATE(2025,1,1),IF(ISNUMBER(SEARCH("2026",$K$1)),DATE(2026,1,1),IF(ISNUMBER(MATCH($K$1,{"January","February","March","April","May","June","July","August","September","October","November","December"},0)),DATE(2025,MATCH($K$1,{"January","February","March","April","May","June","July","August","September","October","November","December"},0),1),DATE(2020,1,1))))), Sales!$B$2:$B$500, "<="&IF(ISNUMBER($K$1),EOMONTH($K$1,0),IF(ISNUMBER(SEARCH("2025",$K$1)),DATE(2025,12,31),IF(ISNUMBER(SEARCH("2026",$K$1)),DATE(2026,12,31),IF(ISNUMBER(MATCH($K$1,{"January","February","March","April","May","June","July","August","September","October","November","December"},0)),EOMONTH(DATE(2025,MATCH($K$1,{"January","February","March","April","May","June","July","August","September","October","November","December"},0),1),0),DATE(2030,12,31))))))} -> 0 | F11: {=SUMIFS(Sales!$M$2:$M$500, Sales!$D$2:$D$500, $B11, Sales!$B$2:$B$500, ">="&IF(ISNUMBER($K$1),DATE(YEAR($K$1),MONTH($K$1),1),IF(ISNUMBER(SEARCH("2025",$K$1)),DATE(2025,1,1),IF(ISNUMBER(SEARCH("2026",$K$1)),DATE(2026,1,1),IF(ISNUMBER(MATCH($K$1,{"January","February","March","April","May","June","July","August","September","October","November","December"},0)),DATE(2025,MATCH($K$1,{"January","February","March","April","May","June","July","August","September","October","November","December"},0),1),DATE(2020,1,1))))), Sales!$B$2:$B$500, "<="&IF(ISNUMBER($K$1),EOMONTH($K$1,0),IF(ISNUMBER(SEARCH("2025",$K$1)),DATE(2025,12,31),IF(ISNUMBER(SEARCH("2026",$K$1)),DATE(2026,12,31),IF(ISNUMBER(MATCH($K$1,{"January","February","March","April","May","June","July","August","September","October","November","December"},0)),EOMONTH(DATE(2025,MATCH($K$1,{"January","February","March","April","May","June","July","August","September","October","November","December"},0),1),0),DATE(2030,12,31))))))} -> 65000 | H11: Office Supplies | I11: {=SUMIFS(Expenses!$D$2:$D$500, Expenses!$B$2:$B$500, $H11, Expenses!$A$2:$A$500, ">="&IF(ISNUMBER($K$1),DATE(YEAR($K$1),MONTH($K$1),1),IF(ISNUMBER(SEARCH("2025",$K$1)),DATE(2025,1,1),IF(ISNUMBER(SEARCH("2026",$K$1)),DATE(2026,1,1),IF(ISNUMBER(MATCH($K$1,{"January","February","March","April","May","June","July","August","September","October","November","December"},0)),DATE(2025,MATCH($K$1,{"January","February","March","April","May","June","July","August","September","October","November","December"},0),1),DATE(2020,1,1))))), Expenses!$A$2:$A$500, "<="&IF(ISNUMBER($K$1),EOMONTH($K$1,0),IF(ISNUMBER(SEARCH("2025",$K$1)),DATE(2025,12,31),IF(ISNUMBER(SEARCH("2026",$K$1)),DATE(2026,12,31),IF(ISNUMBER(MATCH($K$1,{"January","February","March","April","May","June","July","August","September","October","November","December"},0)),EOMONTH(DATE(2025,MATCH($K$1,{"January","February","March","April","May","June","July","August","September","October","November","December"},0),1),0),DATE(2030,12,31))))))} -> 55000 | J11: =IFERROR(I11/$I$15,0) -> 0.14707927 | K11: {=COUNTIFS(Expenses!$B$2:$B$500, $H11, Expenses!$A$2:$A$500, ">="&IF(ISNUMBER($K$1),DATE(YEAR($K$1),MONTH($K$1),1),IF(ISNUMBER(SEARCH("2025",$K$1)),DATE(2025,1,1),IF(ISNUMBER(SEARCH("2026",$K$1)),DATE(2026,1,1),IF(ISNUMBER(MATCH($K$1,{"January","February","March","April","May","June","July","August","September","October","November","December"},0)),DATE(2025,MATCH($K$1,{"January","February","March","April","May","June","July","August","September","October","November","December"},0),1),DATE(2020,1,1))))), Expenses!$A$2:$A$500, "<="&IF(ISNUMBER($K$1),EOMONTH($K$1,0),IF(ISNUMBER(SEARCH("2025",$K$1)),DATE(2025,12,31),IF(ISNUMBER(SEARCH("2026",$K$1)),DATE(2026,12,31),IF(ISNUMBER(MATCH($K$1,{"January","February","March","April","May","June","July","August","September","October","November","December"},0)),EOMONTH(DATE(2025,MATCH($K$1,{"January","February","March","April","May","June","July","August","September","October","November","December"},0),1),0),DATE(2030,12,31))))))} -> 14
B12: Other | C12: {=SUMIFS(Sales!$H$2:$H$500, Sales!$D$2:$D$500, $B12, Sales!$B$2:$B$500, ">="&IF(ISNUMBER($K$1),DATE(YEAR($K$1),MONTH($K$1),1),IF(ISNUMBER(SEARCH("2025",$K$1)),DATE(2025,1,1),IF(ISNUMBER(SEARCH("2026",$K$1)),DATE(2026,1,1),IF(ISNUMBER(MATCH($K$1,{"January","February","March","April","May","June","July","August","September","October","November","December"},0)),DATE(2025,MATCH($K$1,{"January","February","March","April","May","June","July","August","September","October","November","December"},0),1),DATE(2020,1,1))))), Sales!$B$2:$B$500, "<="&IF(ISNUMBER($K$1),EOMONTH($K$1,0),IF(ISNUMBER(SEARCH("2025",$K$1)),DATE(2025,12,31),IF(ISNUMBER(SEARCH("2026",$K$1)),DATE(2026,12,31),IF(ISNUMBER(MATCH($K$1,{"January","February","March","April","May","June","July","August","September","October","November","December"},0)),EOMONTH(DATE(2025,MATCH($K$1,{"January","February","March","April","May","June","July","August","September","October","November","December"},0),1),0),DATE(2030,12,31))))))} -> 350000 | D12: {=SUMIFS(Sales!$I$2:$I$500, Sales!$D$2:$D$500, $B12, Sales!$B$2:$B$500, ">="&IF(ISNUMBER($K$1),DATE(YEAR($K$1),MONTH($K$1),1),IF(ISNUMBER(SEARCH("2025",$K$1)),DATE(2025,1,1),IF(ISNUMBER(SEARCH("2026",$K$1)),DATE(2026,1,1),IF(ISNUMBER(MATCH($K$1,{"January","February","March","April","May","June","July","August","September","October","November","December"},0)),DATE(2025,MATCH($K$1,{"January","February","March","April","May","June","July","August","September","October","November","December"},0),1),DATE(2020,1,1))))), Sales!$B$2:$B$500, "<="&IF(ISNUMBER($K$1),EOMONTH($K$1,0),IF(ISNUMBER(SEARCH("2025",$K$1)),DATE(2025,12,31),IF(ISNUMBER(SEARCH("2026",$K$1)),DATE(2026,12,31),IF(ISNUMBER(MATCH($K$1,{"January","February","March","April","May","June","July","August","September","October","November","December"},0)),EOMONTH(DATE(2025,MATCH($K$1,{"January","February","March","April","May","June","July","August","September","October","November","December"},0),1),0),DATE(2030,12,31))))))} -> 350000 | E12: {=SUMIFS(Sales!$J$2:$J$500, Sales!$D$2:$D$500, $B12, Sales!$B$2:$B$500, ">="&IF(ISNUMBER($K$1),DATE(YEAR($K$1),MONTH($K$1),1),IF(ISNUMBER(SEARCH("2025",$K$1)),DATE(2025,1,1),IF(ISNUMBER(SEARCH("2026",$K$1)),DATE(2026,1,1),IF(ISNUMBER(MATCH($K$1,{"January","February","March","April","May","June","July","August","September","October","November","December"},0)),DATE(2025,MATCH($K$1,{"January","February","March","April","May","June","July","August","September","October","November","December"},0),1),DATE(2020,1,1))))), Sales!$B$2:$B$500, "<="&IF(ISNUMBER($K$1),EOMONTH($K$1,0),IF(ISNUMBER(SEARCH("2025",$K$1)),DATE(2025,12,31),IF(ISNUMBER(SEARCH("2026",$K$1)),DATE(2026,12,31),IF(ISNUMBER(MATCH($K$1,{"January","February","March","April","May","June","July","August","September","October","November","December"},0)),EOMONTH(DATE(2025,MATCH($K$1,{"January","February","March","April","May","June","July","August","September","October","November","December"},0),1),0),DATE(2030,12,31))))))} -> 0 | F12: {=SUMIFS(Sales!$M$2:$M$500, Sales!$D$2:$D$500, $B12, Sales!$B$2:$B$500, ">="&IF(ISNUMBER($K$1),DATE(YEAR($K$1),MONTH($K$1),1),IF(ISNUMBER(SEARCH("2025",$K$1)),DATE(2025,1,1),IF(ISNUMBER(SEARCH("2026",$K$1)),DATE(2026,1,1),IF(ISNUMBER(MATCH($K$1,{"January","February","March","April","May","June","July","August","September","October","November","December"},0)),DATE(2025,MATCH($K$1,{"January","February","March","April","May","June","July","August","September","October","November","December"},0),1),DATE(2020,1,1))))), Sales!$B$2:$B$500, "<="&IF(ISNUMBER($K$1),EOMONTH($K$1,0),IF(ISNUMBER(SEARCH("2025",$K$1)),DATE(2025,12,31),IF(ISNUMBER(SEARCH("2026",$K$1)),DATE(2026,12,31),IF(ISNUMBER(MATCH($K$1,{"January","February","March","April","May","June","July","August","September","October","November","December"},0)),EOMONTH(DATE(2025,MATCH($K$1,{"January","February","March","April","May","June","July","August","September","October","November","December"},0),1),0),DATE(2030,12,31))))))} -> 306000 | H12: Marketing & Media | I12: {=SUMIFS(Expenses!$D$2:$D$500, Expenses!$B$2:$B$500, $H12, Expenses!$A$2:$A$500, ">="&IF(ISNUMBER($K$1),DATE(YEAR($K$1),MONTH($K$1),1),IF(ISNUMBER(SEARCH("2025",$K$1)),DATE(2025,1,1),IF(ISNUMBER(SEARCH("2026",$K$1)),DATE(2026,1,1),IF(ISNUMBER(MATCH($K$1,{"January","February","March","April","May","June","July","August","September","October","November","December"},0)),DATE(2025,MATCH($K$1,{"January","February","March","April","May","June","July","August","September","October","November","December"},0),1),DATE(2020,1,1))))), Expenses!$A$2:$A$500, "<="&IF(ISNUMBER($K$1),EOMONTH($K$1,0),IF(ISNUMBER(SEARCH("2025",$K$1)),DATE(2025,12,31),IF(ISNUMBER(SEARCH("2026",$K$1)),DATE(2026,12,31),IF(ISNUMBER(MATCH($K$1,{"January","February","March","April","May","June","July","August","September","October","November","December"},0)),EOMONTH(DATE(2025,MATCH($K$1,{"January","February","March","April","May","June","July","August","September","October","November","December"},0),1),0),DATE(2030,12,31))))))} -> 15000 | J12: =IFERROR(I12/$I$15,0) -> 0.040112529 | K12: {=COUNTIFS(Expenses!$B$2:$B$500, $H12, Expenses!$A$2:$A$500, ">="&IF(ISNUMBER($K$1),DATE(YEAR($K$1),MONTH($K$1),1),IF(ISNUMBER(SEARCH("2025",$K$1)),DATE(2025,1,1),IF(ISNUMBER(SEARCH("2026",$K$1)),DATE(2026,1,1),IF(ISNUMBER(MATCH($K$1,{"January","February","March","April","May","June","July","August","September","October","November","December"},0)),DATE(2025,MATCH($K$1,{"January","February","March","April","May","June","July","August","September","October","November","December"},0),1),DATE(2020,1,1))))), Expenses!$A$2:$A$500, "<="&IF(ISNUMBER($K$1),EOMONTH($K$1,0),IF(ISNUMBER(SEARCH("2025",$K$1)),DATE(2025,12,31),IF(ISNUMBER(SEARCH("2026",$K$1)),DATE(2026,12,31),IF(ISNUMBER(MATCH($K$1,{"January","February","March","April","May","June","July","August","September","October","November","December"},0)),EOMONTH(DATE(2025,MATCH($K$1,{"January","February","March","April","May","June","July","August","September","October","November","December"},0),1),0),DATE(2030,12,31))))))} -> 1
B13: Total | C13: =SUM(C9:C12) -> 8782108 | D13: =SUM(D9:D12) -> 8505100 | E13: =SUM(E9:E12) -> 277008 | F13: =SUM(F9:F12) -> 6540010 | H13: Rent & Maintenance | I13: {=SUMIFS(Expenses!$D$2:$D$500, Expenses!$B$2:$B$500, $H13, Expenses!$A$2:$A$500, ">="&IF(ISNUMBER($K$1),DATE(YEAR($K$1),MONTH($K$1),1),IF(ISNUMBER(SEARCH("2025",$K$1)),DATE(2025,1,1),IF(ISNUMBER(SEARCH("2026",$K$1)),DATE(2026,1,1),IF(ISNUMBER(MATCH($K$1,{"January","February","March","April","May","June","July","August","September","October","November","December"},0)),DATE(2025,MATCH($K$1,{"January","February","March","April","May","June","July","August","September","October","November","December"},0),1),DATE(2020,1,1))))), Expenses!$A$2:$A$500, "<="&IF(ISNUMBER($K$1),EOMONTH($K$1,0),IF(ISNUMBER(SEARCH("2025",$K$1)),DATE(2025,12,31),IF(ISNUMBER(SEARCH("2026",$K$1)),DATE(2026,12,31),IF(ISNUMBER(MATCH($K$1,{"January","February","March","April","May","June","July","August","September","October","November","December"},0)),EOMONTH(DATE(2025,MATCH($K$1,{"January","February","March","April","May","June","July","August","September","October","November","December"},0),1),0),DATE(2030,12,31))))))} -> 10000 | J13: =IFERROR(I13/$I$15,0) -> 0.026741686 | K13: {=COUNTIFS(Expenses!$B$2:$B$500, $H13, Expenses!$A$2:$A$500, ">="&IF(ISNUMBER($K$1),DATE(YEAR($K$1),MONTH($K$1),1),IF(ISNUMBER(SEARCH("2025",$K$1)),DATE(2025,1,1),IF(ISNUMBER(SEARCH("2026",$K$1)),DATE(2026,1,1),IF(ISNUMBER(MATCH($K$1,{"January","February","March","April","May","June","July","August","September","October","November","December"},0)),DATE(2025,MATCH($K$1,{"January","February","March","April","May","June","July","August","September","October","November","December"},0),1),DATE(2020,1,1))))), Expenses!$A$2:$A$500, "<="&IF(ISNUMBER($K$1),EOMONTH($K$1,0),IF(ISNUMBER(SEARCH("2025",$K$1)),DATE(2025,12,31),IF(ISNUMBER(SEARCH("2026",$K$1)),DATE(2026,12,31),IF(ISNUMBER(MATCH($K$1,{"January","February","March","April","May","June","July","August","September","October","November","December"},0)),EOMONTH(DATE(2025,MATCH($K$1,{"January","February","March","April","May","June","July","August","September","October","November","December"},0),1),0),DATE(2030,12,31))))))} -> 1
H14: Miscellaneous | I14: {=SUMIFS(Expenses!$D$2:$D$500, Expenses!$B$2:$B$500, $H14, Expenses!$A$2:$A$500, ">="&IF(ISNUMBER($K$1),DATE(YEAR($K$1),MONTH($K$1),1),IF(ISNUMBER(SEARCH("2025",$K$1)),DATE(2025,1,1),IF(ISNUMBER(SEARCH("2026",$K$1)),DATE(2026,1,1),IF(ISNUMBER(MATCH($K$1,{"January","February","March","April","May","June","July","August","September","October","November","December"},0)),DATE(2025,MATCH($K$1,{"January","February","March","April","May","June","July","August","September","October","November","December"},0),1),DATE(2020,1,1))))), Expenses!$A$2:$A$500, "<="&IF(ISNUMBER($K$1),EOMONTH($K$1,0),IF(ISNUMBER(SEARCH("2025",$K$1)),DATE(2025,12,31),IF(ISNUMBER(SEARCH("2026",$K$1)),DATE(2026,12,31),IF(ISNUMBER(MATCH($K$1,{"January","February","March","April","May","June","July","August","September","October","November","December"},0)),EOMONTH(DATE(2025,MATCH($K$1,{"January","February","March","April","May","June","July","August","September","October","November","December"},0),1),0),DATE(2030,12,31))))))} -> 87440 | J14: =IFERROR(I14/$I$15,0) -> 0.2338293 | K14: {=COUNTIFS(Expenses!$B$2:$B$500, $H14, Expenses!$A$2:$A$500, ">="&IF(ISNUMBER($K$1),DATE(YEAR($K$1),MONTH($K$1),1),IF(ISNUMBER(SEARCH("2025",$K$1)),DATE(2025,1,1),IF(ISNUMBER(SEARCH("2026",$K$1)),DATE(2026,1,1),IF(ISNUMBER(MATCH($K$1,{"January","February","March","April","May","June","July","August","September","October","November","December"},0)),DATE(2025,MATCH($K$1,{"January","February","March","April","May","June","July","August","September","October","November","December"},0),1),DATE(2020,1,1))))), Expenses!$A$2:$A$500, "<="&IF(ISNUMBER($K$1),EOMONTH($K$1,0),IF(ISNUMBER(SEARCH("2025",$K$1)),DATE(2025,12,31),IF(ISNUMBER(SEARCH("2026",$K$1)),DATE(2026,12,31),IF(ISNUMBER(MATCH($K$1,{"January","February","March","April","May","June","July","August","September","October","November","December"},0)),EOMONTH(DATE(2025,MATCH($K$1,{"January","February","March","April","May","June","July","August","September","October","November","December"},0),1),0),DATE(2030,12,31))))))} -> 8
H15: Total Expenses | I15: =SUM(I9:I14) -> 373948 | J15: =SUM(J9:J14) -> 1 | K15: =SUM(K9:K14) -> 48

Sheet Sales
A1: Serial No | B1: Date | C1: Client Name | D1: Care Of | E1: Country | F1: Service | G1: Vendor | H1: Total Amount | I1: Received Amount | J1: Balance Receivable | K1: Vendor Cost | L1: Vendor Status | M1: Gross Profit
A2: 1 | B2: 45662 | C2: Usman | D2: Zeeshan | E2: Germany | F2: Profile | G2: In-House | H2: 50000 | I2: 50000 | J2: =IF(H2="","",H2-N(I2)) -> 0 | K2: 0 | L2: N/A | M2: =IF(H2="","",H2-N(K2)) -> 50000
A3: 2 | B3: 45665 | C3: Hussain Ali Hashmi | D3: Zeeshan | E3: New Zealand | F3: Profile + Visa Fee | G3: Embassy | H3: 145000 | I3: 145000 | J3: =IF(H3="","",H3-N(I3)) -> 0 | K3: 73500 | L3: Paid | M3: =IF(H3="","",H3-N(K3)) -> 71500
A4: 3 | B4: 45667 | C4: Hamza Maqbool | D4: Zeeshan | E4: Belgium | F4: Profile + Appointment | G4: In-House | H4: 70000 | I4: 58000 | J4: =IF(H4="","",H4-N(I4)) -> 12000 | K4: 0 | L4: N/A | M4: =IF(H4="","",H4-N(K4)) -> 70000
A5: 4 | B5: 45669 | C5: Komal | D5: Kamal | E5: Singapore | F5: Visa | G5: Nawander | H5: 25000 | I5: 25000 | J5: =IF(H5="","",H5-N(I5)) -> 0 | K5: 15000 | L5: Paid | M5: =IF(H5="","",H5-N(K5)) -> 10000
A6: 5 | B6: 45671 | C6: Adnan | D6: Kamal | E6: Singapore | F6: Visa | G6: Nawander | H6: 25000 | I6: 25000 | J6: =IF(H6="","",H6-N(I6)) -> 0 | K6: 15000 | L6: Paid | M6: =IF(H6="","",H6-N(K6)) -> 10000
A7: 6 | B7: 45673 | C7: Hassan Muraad | D7: Kamal | E7: Singapore | F7: Visa | G7: Nawander | H7: 25000 | I7: 25000 | J7: =IF(H7="","",H7-N(I7)) -> 0 | K7: 15000 | L7: Paid | M7: =IF(H7="","",H7-N(K7)) -> 10000
A8: 7 | B8: 45675 | C8: Khuram Khan | D8: Kamal | E8: Singapore | F8: Visa | G8: Nawander | H8: 20000 | I8: 20000 | J8: =IF(H8="","",H8-N(I8)) -> 0 | K8: 15000 | L8: Paid | M8: =IF(H8="","",H8-N(K8)) -> 5000
A9: 8 | B9: 45677 | C9: Komal | D9: Kamal | E9: Malaysia | F9: Visa | G9: Fakhar | H9: 50000 | I9: 50000 | J9: =IF(H9="","",H9-N(I9)) -> 0 | K9: 13000 | L9: Paid | M9: =IF(H9="","",H9-N(K9)) -> 37000
A10: 9 | B10: 45679 | C10: Adnan | D10: Kamal | E10: Malaysia | F10: Visa | G10: Fakhar | H10: 50000 | I10: 50000 | J10: =IF(H10="","",H10-N(I10)) -> 0 | K10: 13000 | L10: Paid | M10: =IF(H10="","",H10-N(K10)) -> 37000
A11: 10 | B11: 45682 | C11: Muhammad Atthar | D11: Zeeshan | E11: Spain | F11: Work Visa Appointment | G11: Nomi | H11: 200000 | I11: 17000 | J11: =IF(H11="","",H11-N(I11)) -> 183000 | K11: 150000 | L11: Pending | M11: =IF(H11="","",H11-N(K11)) -> 50000
A12: 11 | B12: 45685 | C12: Safeer Sir | D12: Kamal | E12: Portugal | F12: Insurance | G12: Adamjee | H12: 6000 | I12: 6000 | J12: =IF(H12="","",H12-N(I12)) -> 0 | K12: 4125 | L12: Paid | M12: =IF(H12="","",H12-N(K12)) -> 1875
A13: 12 | B13: 45690 | C13: Parveen | D13: Zeeshan | E13: France | F13: Other | G13: Shahzaib | H13: 135000 | I13: 135000 | J13: =IF(H13="","",H13-N(I13)) -> 0 | K13: 0 | L13: N/A | M13: =IF(H13="","",H13-N(K13)) -> 135000
... A166: 165 | B166: 46253 | C166: Ayesha & Noreen Ilyas | D166: Kamal | E166: Portugal | F166: Apostille | G166: KTS Services | H166: 90000 | I166: 90000 | J166: =IF(H166="","",H166-N(I166)) -> 0 | K166: 53000 | L166: Paid | M166: =IF(H166="","",H166-N(K166)) -> 37000
A167: Total | H167: =SUM(H2:H166) -> 17896531 | I167: =SUM(I2:I166) -> 17384523 | J167: =SUM(J2:J166) -> 512008 | K167: =SUM(K2:K166) -> 7517528 | M167: =SUM(M2:M166) -> 10379003

Sheet Expenses
A1: Date | B1: Category | C1: Expense Item | D1: Amount | E1: Paid To | F1: Payment Method | G1: Notes
A2: 45662 | B2: Utilities | C2: Water Bill | D2: 5000 | E2: Office | F2: Cash | G2: Water utility bill
A3: 45664 | B3: Office Supplies | C3: Printer & Mouse | D3: 5000 | E3: Vendor | F3: Cash | G3: Computer accessories
A4: 45667 | B4: Salaries & Wages | C4: Contractor / Staff Fee | D4: 14600 | E4: Atif | F4: Cash | G4: Payment to Atif Bhai
A5: 45669 | B5: Salaries & Wages | C5: Staff Salary / Stipend | D5: 11000 | E5: Haseeb | F5: Cash | G5: Payment to Haseeb
A6: 45672 | B6: Office Supplies | C6: Office Furniture | D6: 20000 | E6: Vendor | F6: Cash | G6: Furniture for office
A7: 45675 | B7: Marketing & Media | C7: Video Stand | D7: 5000 | E7: Vendor | F7: Online | G7: Video recording equipment
A8: 45677 | B8: Marketing & Media | C8: Video Editor | D8: 1000 | E8: Other | F8: Online | G8: Editing services
A9: 45679 | B9: Utilities | C9: Electricity Bill | D9: 2600 | E9: Office | F9: Online | G9: Monthly electricity bill
A10: 45682 | B10: Utilities | C10: PTCL Internet & Phone | D10: 1500 | E10: Noman | F10: Online | G10: PTCL bill paid via Noman
A11: 45685 | B11: Marketing & Media | C11: Hamza Application | D11: 12500 | E11: Hamza | F11: Online | G11: Mobile app development
A12: 45687 | B12: Miscellaneous | C12: General Office Expenses | D12: 1200 | E12: Office | F12: Cash | G12: Sundry office expenses
A13: 45693 | B13: Office Supplies | C13: Office Grocery | D13: 3000 | E13: Office | F13: Cash | G13: Grocery via Tayyab (Paid by Zeeshan)
... A140: 46218 | B140: Rent & Maintenance | C140: Plaza ASM Fee | D140: 10000 | E140: Plaza Management | F140: Cash | G140: Paid by Zeeshan
C141: Total Expenses | D141: =SUM(D2:D140) -> 1127578

Sheet Partner Settlement
A1: Date | B1: Partner Name | C1: Transaction Type | D1: Amount | E1: Notes / Reference
A2: 45659 | B2: Mughees | C2: Capital Advance | D2: 527000 | E2: Initial TRP opening balance
A3: 45667 | B3: Mughees | C3: Receipt | D3: 150000 | E3: Installment received
A4: 45672 | B4: Zeeshan | C4: Partner Drawing | D4: 100000 | E4: 50,000 + 50,000 received by Zeeshan
A5: 45677 | B5: Kamal | C5: Partner Drawing | D5: 100000 | E5: Received by Kamal Bhai
A6: 45682 | B6: Mughees | C6: Receipt | D6: 50000 | E6: Installment received
A7: 45687 | B7: Mughees | C7: Receipt | D7: 30000 | E7: Installment received
A8: 45713 | B8: Kamal | C8: Partner Drawing | D8: 50000 | E8: Dated 25-02-2025 Kamal Bhai
A9: 45688 | B9: Kamal | C9: Settlement | D9: 25450 | E9: Remaining January 2025 net balance
A10: 45747 | B10: Zeeshan | C10: Profit Distribution | D10: 46248 | E10: March profit distribution
A11: 45747 | B11: Kamal | C11: Profit Distribution | D11: 46248 | E11: March profit distribution
A12: 45790 | B12: Kamal | C12: Partner Disbursement | D12: 30000 | E12: Appointment payment disbursed by Kamal
A13: 45796 | B13: Kamal | C13: Partner Disbursement | D13: 10000 | E13: Credit Ammar disbursed by Kamal
... A36: 46247 | B36: Kamal | C36: Partner Drawing | D36: 29500 | E36: Share from Italy Appointment Group
B37: Total | D37: =SUM(D2:D36) -> 1713246

Sheet january 
E4: JANUARY SALE
C7: Serial number | D7: client name | E7: Care of | F7: country | G7: Vender | H7: services | I7: received amount | J7: Payable
C8: 1 | D8: usman | E8: zeeshan | F8: Germany | H8: profile | I8: 50000 | K8: 50000
C9: 2 | D9: hussain ali hashmi | E9: zeeshan | F9: New Zealand | H9: profile + visa fee | I9: 145000 | J9: 73500 | K9: 71500 | O9: 5000 | P9: water bill
C10: 4 | D10: hamza maqboool | E10: zeeshan | F10: Belgium | H10: profile + appointment | I10: 70000 | K10: 58000 | O10: 5000 | P10: printer & mouse
C11: 5 | D11: komal | E11: Kamal | F11: Singapore | G11: Nawander | H11: visa | I11: 25000 | J11: 15000 | O11: 14600 | P11: atif bahi
C12: 6 | D12: Adnan | E12: Kamal | F12: Singapore | G12: Nawander | H12: visa | I12: 25000 | J12: 15000 | O12: 11000 | P12: haseeb
C13: 7 | D13: Hassan muraad | E13: Kamal | F13: Singapore | G13: Nawander | H13: visa | I13: 25000 | J13: 15000
C14: 8 | D14: Khuram khan | E14: Kamal | F14: Singapore | G14: Nawander | H14: visa | I14: 20000 | J14: 15000 | O14: 20000 | P14: furniture
C15: 9 | D15: komal | E15: Kamal | F15: Malaysia | G15: Fakhar | H15: visa | I15: 50000 | J15: 13000 | O15: 5000 | P15: video stand
C16: 10 | D16: adnan | E16: Kamal | F16: Malaysia | G16: Fakhar | H16: visa | I16: 50000 | J16: 13000 | O16: 1000 | P16: video editor
C17: 11 | D17: Muhammad atthar | E17: zeeshan | F17: spain | G17: Nomi | H17: work visa appointment | I17: 200000 | J17: 150000 | L17: 17000 received | O17: 2600 | P17: electrcity
C18: 12 | D18: safeer sir | E18: Kamal | F18: portugal | G18: Adamjee | H18: insurance | I18: 6000 | J18: 4125 | K18: received online | L18: zeeshan | O18: 1500 | P18: noman ptcl
C19: 13 | I19: =SUM(I8:I18) -> 666000 | J19: =SUM(J9:J18) -> 313625 | O19: 12500 | P19: app hamza
C20: 15 | O20: 1200 | P20: office expenses
O21: =SUM(O11:O20) -> 69400
D23: Mughees | E23: kamal | F23: TRP | G23: 527000
G24: 150000 received | J24: 25450 remaning january 2025
G25: 50000 + 50000 received | H25: zeeshan
G26: 100000 | H26: kamal bahi
G27: 50000 dated 25-02-2025 | H27: kamal bahi
G28: 327000 | H28: remaning
G29: 50000 | H29: received
G30: 277000 | H30: remaning
G31: 30000 | H31: received
G32: 247000 | H32: remaning

Sheet February
E4: FEBRUARY SALE
C7: Serial number | D7: client name | E7: Care of | F7: country | G7: Vender | H7: services | I7: received amount | J7: Payable | K7: profit | L7: payable to company | Q7: s
C8: 1 | D8: Parveen | E8: zeeshan | F8: france | G8: shahzaib | H8: appointment | I8: 135000 | N8: Return to madam parveen 20/02/2025
C9: 2 | D9: Teepo bahi | E9: zeeshan | F9: Saudia | G9: shahzad BSM | H9: umrah visa | I9: 41900 | J9: 40000 | K9: 1900 | L9: =1900/2 -> 950 | M9: 1900 company account
C10: 4 | D10: TST payment | E10: kamal | F10: Philippines | H10: Diplomatic entry | I10: 26000
C11: 5 | D11: hamza ali | E11: kamal | F11: Thailand | G11: imtiaz | H11: visa | I11: 23000 | J11: 14500 | K11: 8500 | L11: 8500
C12: 6 | D12: Ghayas ud din | E12: kamal | F12: Thailand | G12: imtiaz | H12: visa | I12: 23000 | J12: 14500 | K12: 8500 | L12: 8500
C13: 7 | D13: abdul hafeez | E13: zeeshan | F13: france | G13: adamjee | H13: insurance | I13: 12000 | J13: 7192 | K13: 4808 | L13: =4808/2 -> 2404 | M13: company account | O13: 12000 transferd company account | S13: paid by
C14: 8 | D14: asif ali | E14: zeeshan | F14: schengen / worldwide | G14: adamjee | H14: insurance
C15: 9 | D15: salman | E15: zeeshan | F15: new zealand | G15: Shoukat sir | H15: new zealand visa | I15: 130000 | J15: 83650 | K15: =I15-J15 -> 46350 | L15: =K15/2 -> 23175
C16: 10 | D16: raja amir refique | E16: kamal | F16: canada | G16: kamal express | H16: canada appointment | I16: 23000 | J16: 0 | K16: 23000 | L16: 23000 | R16: zeeshan | S16: 3000 | V16: tayyab | W16: grocery
C17: 11 | D17: sabhat hameed | E17: kamal | F17: sri lanka | G17: kamal express | H17: visa | I17: 14000 | J17: 8300 | K17: =I17-J17 -> 5700 | L17: 5700 | R17: zeeshan | S17: 400 | V17: pure crystel
C18: 12 | D18: Mubasher rehman | E18: kamal | F18: Saudia | G18: Flay must | H18: visa | I18: 45000 | J18: 40905 | K18: 4905 | L18: =I18-J18 -> 4095 | M18: paid madam rehana | R18: zeeshan | S18: 4000 | V18: office dinner | W18: tahir attock
C19: 13 | D19: Saira faisal | E19: Kamal | F19: spain | G19: adamjee | H19: insurance | I19: 12000 | J19: received onile | T19: kamal | U19: 1000 | V19: water bill
C20: 14 | D20: Saira faisal | E20: kamal | F20: spain | G20: kamal express | H20: visa services | T20: kamal | U20: 3000 | V20: office expenses | W20: 24/02/2025
C21: 15 | D21: sibtul hassan | E21: zeeshan | F21: spain | G21: zeeshan | H21: visa letter | I21: 4000 | J21: 0 | K21: 4000 | L21: 2000 | R21: zeeshan | U21: 2000 | V21: video editor
C22: 16 | D22: Mubasher rehman | E22: kamal | F22: Saudia | G22: saqib | H22: ticket | I22: 289000 | J22: 272000 | K22: =I22-J22 -> 17000 | L22: 17000
C23: 17 | D23: Muhammad Tahir | E23: kamal | F23: france | G23: adamjee | H23: insurance | I23: paid | T23: kamal | U23: 740 | V23: tissue and black tea | W23: 25/02/2025
C24: 18 | D24: Nasir Iqbal | E24: zeeshan | F24: austria | H24: visa services | I24: 75000 | J24: 13000 | K24: =I24-J24 -> 62000 | L24: =K24/2 -> 31000 | R24: zeeshan | U24: 6350 | V24: iseco bill zeeshan | W24: 26/02/2025
C25: 19 | R25: zeeshan | U25: 400 | V25: indrive
C26: 20 | T26: kamal | U26: 15000 | V26: tayyab salary
C27: 21
C28: 22
C29: 23
C30: 24
C31: 25
C32: 26
C33: 27
C34: 28
C35: 29
C36: 30

Sheet March
E2: MARCH SALE
T4: office expnses
C6: Serial number | D6: client name | E6: Care of | F6: country | G6: Vender | H6: services | I6: total amount | J6: Payable | K6: status | L6: profit | M6: payable to company | N6: account
C7: 1 | D7: Armoghan akbar | E7: kamal | F7: UAE | G7: saqib | H7: ticket | I7: 47000 | J7: 45500 | K7: received account kamal | L7: 1500 | M7: 1500 | N7: kamal ahmed | U7: amount | V7: payto | W7: zeeshan/kamal | X7: dated
C8: 2 | D8: sumira butt | E8: kamal | F8: saudia | G8: zaka bahi | H8: MOFA | I8: 3500 | J8: 2500 | K8: received cash kamal | L8: 1000 | M8: 1000 | N8: kamal ahmed | U8: 1000 | V8: plaza water bill | W8: kamal | X8: 13/03/2025
C9: 4 | D9: sumira butt | E9: kamal | F9: saudia | G9: aqib transworld | H9: translation | I9: 4500 | J9: 3000 | K9: received csah kamal | L9: 1500 | M9: 1500 | N9: kamal ahmed | U9: 1000 | V9: video editior | W9: zeeshan | X9: 18/03/2025
C10: 5 | D10: usman rasheed | E10: zeeshan | F10: Azerbaijan | G10: kamal express | H10: visa | I10: 17000 | J10: 8500 | K10: received account zeeshan | L10: 8500 | M10: 4250 | N10: zeeshan siddique | U10: 2790 | V10: ptcl bill | W10: kamal | X10: 20/03/2025
C11: 7 | D11: mahnoor imtiaz | E11: zeeshan | F11: hungary | G11: zeeshan | H11: business appointment | I11: 30000 | J11: 5125 | K11: received account zeeshan | L11: =I11-J11 -> 24875 | M11: =L11/2 -> 12437.5 | N11: zeeshan siddique | U11: 4309 | V11: iseco bill | W11: kamal | X11: 26/03/2025
C12: 8 | D12: muhammad faiq khan | E12: zeeshan | F12: hungary | G12: zeeshan | H12: business appointment | I12: 30000 | J12: 5125 | K12: received account zeeshan | L12: =I12-J12 -> 24875 | M12: =L12/2 -> 12437.5 | N12: zeeshan siddique | U12: 17000 | V12: tayyab | W12: kamal | X12: 24/03/2025
C13: 9 | D13: syeda iqra batool | E13: zeeshan | F13: Lithuania | G13: salman | H13: Lithuania appointment | I13: 25000 | J13: 15625 | K13: received account zeeshan | L13: =I13-J13 -> 9375 | M13: =L13/2 -> 4687.5 | N13: zeeshan siddique | U13: 26099 | V13: total
C14: 10 | D14: jamshad anwar | E14: zeeshan | F14: estonia | G14: zeeshan | H14: estonia appointment | I14: 30000 | J14: 5125 | K14: received account zeeshan | L14: 24875 | M14: =L14/2 -> 12437.5 | N14: zeeshan siddique | U14: =U13*40/100 -> 10439.6
C15: 11 | D15: ayesha tanveer | E15: kamal | F15: france | G15: salman | H15: visa appointment | I15: 140000 | J15: 75000 | K15: received kamal account | L15: 65000 | N15: kamal ahmed
C16: 12 | D16: tanveer hussain | E16: kamal | F16: france | G16: salman | H16: visa appointment | I16: 140000 | J16: 75000 | K16: received kamal account | L16: 65000 | N16: kamal ahmed
C17: 13 | D17: meer hadi | E17: kamal | F17: Azerbaijan | G17: saqib | H17: ticket | I17: 155400 | J17: 138500 | K17: received kamal account | L17: =I17-J17 -> 16900 | M17: 16900
C18: 14 | D18: asghar arslan | E18: kamal | F18: Azerbaijan | G18: saqib | H18: ticket | I18: 155400 | J18: 138500 | K18: received kamal account | L18: =I18-J18 -> 16900 | M18: 16900
C19: 15
C20: 16
C21: 17
C22: 18
C23: 19 | H23: zeeshan pay to company total amount 50%
C24: 20
C25: 21
C26: 22 | H26: total profit | I26: 92496
C27: 23 | H27: zeeshan | I27: 46248
C28: 24 | H28: kamal | I28: 46248
C29: 25
C30: 26
C31: 27
C32: 28
C33: 29
C34: 30

Sheet April
E2: APRIL SALE
V4: office expnses
C6: Serial number | D6: client name | E6: Care of | F6: country | G6: Vender | H6: services | I6: total amount | J6: Payable | K6: cost | L6: S/C | M6: status | N6: profit | O6: payable to company | P6: account
C7: 1 | D7: Ajmal hussain | E7: kamal | F7: oman | G7: saqib | H7: ticket | I7: 39500 | J7: 36472 | K7: 34972 | L7: 1500 | M7: pending | N7: =I7-J7 -> 3028 | W7: amount | X7: payto | Y7: zeeshan/kamal | Z7: dated
C8: 2 | D8: Muhammad Ifrahim | E8: kamal | F8: oman | G8: saqib | H8: ticket | I8: 39500 | J8: 36472 | K8: 34972 | L8: 1500 | M8: pending | N8: 3028 | W8: 1250 | X8: waqas video editor | Y8: zeeshan
C9: 4 | D9: faiq khan | E9: zeeshan | F9: hungary | G9: kamal express | H9: visa | I9: 37500 | M9: received zeeshasn | W9: 3130 | X9: ptcl | Y9: kamal
C10: 5 | D10: mahnoor imtiaz | E10: zeeshan | F10: hungary | G10: kamal express | H10: visa | I10: 37500 | M10: received zeeshasn
C11: 7 | D11: Abdul hameed | E11: kamal | F11: kenya | G11: kamal express | H11: visa | I11: 75000 | M11: received kamal
C12: 8 | D12: Usman Rasheed | E12: zeeshan | G12: saqib / TST / adamjee | H12: ticket / hotel / insurance | I12: 992000 | J12: 930000 | K12: 870000 | L12: 15000 | M12: received company account | N12: =I12-J12 -> 62000
C13: 9 | D13: tanveer appointments | E13: kamal | F13: Netherlands | G13: kamal express | H13: visa appointments | I13: 10000 | M13: received zeeshasn | N13: 10000
C14: 10 | D14: mujeeb zahoor | E14: kamal | G14: diplomatic /police | H14: diplomatic entry | I14: 8000 | J14: 6000 | N14: 2000
C15: 11 | D15: syed Nouman | E15: kamal | F15: UK | H15: visa form checking | I15: 15000 | J15: 0 | K15: 0 | L15: 0 | M15: cash kamal | N15: 15000
C16: 12
C17: 13
C18: 14
C19: 15
C20: 16
C21: 17
C22: 18
C23: 19
C24: 20
C25: 21
C26: 22
C27: 23
... C34: 30

Sheet May 
E2: MAY 2025 SALE
W4: office expnses
C6: Serial number | D6: client name | E6: Care of | F6: country | G6: payment Date | H6: Vender | I6: services | J6: total amount | K6: Payable | L6: cost | M6: S/C | N6: status | O6: profit | P6: payable to company | Q6: account
C7: 1 | D7: Muhammad Ali khan | E7: zeeshan | F7: france | G7: 45782 | H7: adamjee | I7: insurance | J7: 15000 | N7: received zeeshan account | X7: amount | Y7: payto | Z7: zeeshan/kamal | AA7: dated
C8: 2 | D8: Shahzad arif | E8: zeeshan | F8: Norway | G8: 45874 | H8: kamal express & holidays pvt ltd | I8: appointment | J8: 38000 | K8: 5500 | N8: received zeeshan account | X8: 1000 | Y8: crystel water | Z8: zeeshan | AA8: 45782
C9: 4 | D9: waqas refique | E9: zeeshan | F9: Lithuania | G9: 45996 | H9: kamal express & holidays pvt ltd | I9: appointment | J9: 30000 | K9: 4500 | L9: =K9*4 -> 18000 | N9: received zeeshan account | X9: 15000 | Y9: Tayyab salary | Z9: zeeshan | AA9: 45996
C10: 5 | D10: saqib ramzan | E10: zeeshan | F10: Lithuania | G10: 45996 | H10: kamal express & holidays pvt ltd | I10: appointment | J10: 30000 | K10: 4500 | N10: received zeeshan account | X10: 2000 | Y10: grocery | Z10: zeeshan | AA10: 45996
C11: 7 | D11: saeed ahmad | E11: zeeshan | F11: Lithuania | G11: 45996 | H11: kamal express & holidays pvt ltd | I11: appointment | J11: 30000 | K11: 4500 | N11: received zeeshan account | X11: 1000 | Y11: irshad water bill | Z11: zeeshan | AA11: 13/5/2025
C12: 8 | D12: asad munir | E12: kamal | F12: hungary | G12: remaning | H12: kamal express & holidays pvt ltd | I12: appointment | N12: payement remaning | X12: 4706 | Y12: iseco bill | Z12: zeeshan | AA12: 21/5/2025
C13: 12 | D13: Naila sarwar | E13: zeeshan | F13: Portugal | G13: 26/05/2025 & 27/05/2025 | H13: sarmad | I13: appointment | J13: 490000 | K13: 110000 | N13: received zeeshan account | X13: 15400 | Y13: Patty cash food | Z13: zeeshan | AA13: 31/05/2025
C14: 13 | D14: kamran shah | E14: kamal | F14: malaysia | H14: fakhar / shabar travel | I14: visa | J14: 20000 | K14: 26000 | X14: 90000 | Y14: office rent | Z14: kamal | AA14: 45843
C15: 14 | D15: Shahzad arif | E15: Zeeshan | F15: Norway | G15: 45663 | H15: kamal express & holidays pvt ltd | I15: Consultancy | J15: 70000 | K15: 3500 | N15: received zeeshan account | O15: 13500 | P15: 3500 INS to KAMAL EXP ACCOUNT | X15: 3800 | Y15: PTCL Bill | Z15: kamal | AA15: 21/05/2025
C16: 15
C17: 16 | Y17: KAMAL AHMED
C18: 17 | X18: 30000 | Y18: appointment | Z18: kamal | AA18: 13/05/2025
C19: 18 | X19: 10000 | Y19: credit ammar | Z19: kamal | AA19: 19/0/2025
C20: 19 | G20: paid appointment fee | X20: 35000 | Y20: raja ammar refund | Z20: kamal | AA20: 19/05/2025
C21: 20 | F21: =SUM(J8:J11) -> 128000 | G21: 37000
C22: 21 | F22: =F21-G21 -> 91000 | W22: zeeshan | X22: =SUM(X8:X13) -> 39106 | Y22: =X22/2 -> 19553 | Z22: 19553
C23: 22 | W23: kamal | X23: =SUM(X14:X15) -> 93800 | Y23: =X23/2 -> 46900 | Z23: 46000
C24: 23 | Z24: =Z23-Z22 -> 26447
C25: 24
C26: 25
C27: 26
C28: 27
C29: 28
C30: 29
C31: 30

Sheet JUNE 2025
E2: JUNE 2025 SALE
W4: office expnses
C6: Serial number | D6: client name | E6: Care of | F6: country | G6: payment Date | H6: Vender | I6: services | J6: total amount | K6: Payable | L6: cost | M6: S/C | N6: status | O6: profit | P6: payable to company | Q6: account | W6: 15000 | X6: tayyab salary | Y6: 45783 | Z6: kamal
C7: 1 | D7: Jahanzaib Shahbbir | E7: zeeshan | F7: hungary | G7: 16/05/2025 | H7: Salman | I7: appointment | J7: 60000 | K7: 17000 | L7: 17000 | N7: 30k received zeeshan account | O7: 13000 | W7: 2400 | X7: grocery | Y7: 16/06/2025 | Z7: kamal
C8: 2 | D8: usman rasheed | E8: zeeshan | F8: hungary /Malaysia visa | G8: 45997 | H8: kamal express & holidays pvt ltd | I8: appointment | J8: 105000 | K8: 18+9 | N8: received zeeshan account | W8: 6934 | X8: iseco bill | Z8: zeeshan
C9: 3 | D9: muhamamd asif & Fauzia asif | E9: kamal | F9: hungary | G9: 45753 | H9: kamal express & holidays pvt ltd | I9: appointment | J9: 45000 | K9: 9000 | L9: 36000 | N9: received kamal account | W9: 1150 | X9: hardwear | Y9: 22/06/2025 | Z9: zeeshan
C10: 4 | D10: wajahat shafiq | E10: zeeshan | F10: hungary | G10: 45783 | H10: kamal express & holidays pvt ltd | I10: appointment | J10: 25000 | K10: 4500 | L10: 20500 | N10: received zeeshan account | W10: 680 | X10: hardwear | Y10: 25/06/2025 | Z10: zeeshan
C11: 5 | D11: Mishal | E11: kamal | F11: spain | H11: Noman kazmi | I11: appointment | W11: 4818 | X11: grocery | Y11: different dates | Z11: zeeshan
C12: 6 | D12: Rayan | E12: kamal | F12: spain | H12: Noman kazmi | I12: appointment | W12: 11370 | X12: lunch | Y12: month of june | Z12: zeeshan/ kamal | AA12: kamal paid 2320 | AB12: zeeshan paid 9050
C13: 7 | D13: hibba | E13: kamal | F13: spain | H13: Noman kazmi | I13: appointment | W13: 25000 | X13: hardwear phone | Y13: 20/06/2025 | Z13: zeeshan
C14: 8 | D14: saeed ahmad | E14: zeeshan | F14: hungary | G14: 45967 | H14: kamal express & holidays pvt ltd | I14: profile | J14: 40000 | N14: received zeeshan account | W14: 43000 | X14: hardwear laptop
C15: 9 | D15: saqib ramzan | E15: zeeshan | F15: hungary | G15: 13/06/2025 | H15: kamal express & holidays pvt ltd | I15: profile | J15: 40000 | N15: received zeeshan account
C16: 10 | D16: waqas refique | E16: zeeshan | F16: hungary | G16: 16/06/2025 | H16: kamal express & holidays pvt ltd | I16: profile | J16: 33000 | N16: received zeeshan account
C17: 11 | D17: nasir iqbal | E17: zeeshan | F17: Malaysia | G17: 18/06/2025 | H17: wasif ullah khan | I17: visa | J17: 25000 | K17: 18000 | N17: received zeeshan account
C18: 12 | D18: spain appointment kazmi bls | E18: zeeshan | F18: spain | G18: 15/06/2025 | H18: zeeshan siddique | I18: appointment | J18: 6500 | K18: 5015 | N18: received zeeshan account
C19: 13 | D19: Raja shahzaib sultan | E19: zeeshan | F19: Malaysia | G19: 10k remaning shahzaib bahi | H19: wasif ullah khan | I19: visa | J19: 15000 | K19: 13000 | L19: 20000
C20: 14 | D20: Healon | E20: zeeshan | F20: Netherlands | G20: 20/06/2025 | H20: kamal express & holidays pvt ltd | I20: appointment/profiling | N20: received kamal express account
C21: 15 | D21: M saim jan | E21: zeeshan | F21: italy | G21: remaning | H21: salman shah | I21: study appointment
C22: 16 | D22: mujeeb ullah zahoor | E22: kamal | F22: Singapore
C23: 17 | D23: Ray Muhmmad Ahmad | E23: kamal | F23: Singapore
C24: 18 | D24: Ray Muhmmad Usman | E24: kamal | F24: Singapore
C25: 14 | D25: Ayesha Anwar | E25: kamal | F25: Singapore
C26: 14 | D26: Zaha Mujeeb | E26: kamal | F26: Singapore
C39: 45753 | D39: 20000 | E39: zeeshan received | F39: from kamal ahmed
C40: 45814 | D40: 20000 | E40: kamal received | F40: from zeeshan siddique
C41: 16/06/2025 | D41: 43000 | E41: kamal received | F41: feom zeeshan account

Sheet JULY 2025
E2: JULY 2025 SALE
W4: office expnses
C6: Serial number | D6: client name | E6: Care of | F6: country | G6: payment Date | H6: Vender | I6: services | J6: total amount | K6: Payable | L6: cost | M6: S/C | N6: status | O6: profit | P6: payable to company | Q6: account | W6: 3597 | X6: Grocery | Y6: 45876 | Z6: Zeeshan
C7: 1 | D7: Ali Raza | E7: kamal | F7: New Zealand | G7: 45907 | H7: Adam jee insurance | I7: insurance | J7: 11700 | N7: kamal bahi account | W7: 2400 | X7: water bill | Y7: 45937 | Z7: Zeeshan
C8: 2 | D8: shahroze & Mishaal | E8: zeeshan | F8: Indonesia | H8: zohaib | I8: visa | J8: 70000 | K8: 42000+800 ins | W8: 2610 | X8: Grocery | Y8: 18/07/2025 | Z8: Zeeshan
C9: 3 | D9: Husanain ali | E9: zeeshan | F9: turkey | G9: 15/07/2025 | H9: kamal express & holidays | I9: file | J9: 20000 | K9: 0 | N9: company account | Q9: company account | W9: 1000 | X9: water bill plaza | Y9: 18/07/2025 | Z9: kamal
C10: 4 | D10: Imran | E10: kamal | F10: Portugal | G10: 21/07/2025 | H10: Tanveer | I10: (MOFA) Appostile | J10: 24300 | K10: 17000 | N10: kamal sir cash | Q10: kamal sir cash | W10: 3790 | X10: PTCL bill | Y10: 21/07/2025 | Z10: kamal
C11: 5 | D11: Aroosa junaid | E11: zeeshan | F11: italy | G11: 24/07/2025 | H11: waleed | I11: Appointment | J11: 300000 | K11: 50000 | N11: Zeeshan account | O11: 250000 | P11: 125000 kamal bahi account | W11: 2000 | X11: Grocery | Y11: 21/07/2025 | Z11: kamal
C12: 6 | D12: zahid mehmood | E12: zeeshan | F12: spain | G12: 24/07/2025 | H12: kamal express & holidays | I12: Appointment | J12: 60000 | K12: 21000 | N12: Zeeshan account | P12: 15000 kamal bahi account | W12: 25000 | X12: meeting E11 | Y12: 45723 | Z12: Zeeshan
C13: 7 | W13: 5141 | X13: Grocery | Y13: 28/07/2025 | Z13: Zeeshan
C14: 8 | W14: 13099 | X14: iseco bill | Y14: 21/07/2025 | Z14: Zeeshan
C15: 9 | W15: 7500 | X15: Ac cost | Y15: Different dates july | Z15: Zeeshan
C16: 10 | W16: 500 | X16: Laptop cabel | Y16: 45907 | Z16: Zeeshan
C17: 3 | W17: 1120 | X17: TCS | Y17: 07/02 july 2025 | Z17: Zeeshan
W18: 10000 | X18: talha italy boot | Y18: 45968 | Z18: kamal
W19: 50000 | X19: talha italy boot | Y19: 45968 | Z19: zeeshan
C20: 14 | W20: 14256 | X20: lunch | Y20: july | Z20: zeeshan & kamal | AA20: 2210 kamal | AB20: 12046 Zeeshan
X25: 48013 | Y25: ZEESHAN | Z25: 75000 | AA25: Meeting + app boot
X26: 9000 | Y26: KAMAL | Z26: 10000 | AA26: app boot
C41: 45753 | D41: 20000 | E41: zeeshan received | F41: from kamal ahmed
C42: 45814 | D42: 20000 | E42: kamal received | F42: from zeeshan siddique
C43: 16/06/2025 | D43: 43000 | E43: kamal received | F43: feom zeeshan account

Sheet AUG 2025 
E2: AUG 2025 SALE
W4: office expnses
C6: Serial number | D6: client name | E6: Care of | F6: country | G6: payment Date | H6: Vender | I6: services | J6: total amount | K6: Payable | L6: cost | M6: S/C | N6: status | O6: profit | P6: payable to company | Q6: account | W6: amount | X6: items | Y6: date | Z6: zeeshan / kamal
C7: 1 | D7: Jamala sahib & jan shabir | E7: zeeshan | F7: Sweden | G7: 45877 | H7: kamal express | I7: appointment | J7: 70000 | K7: 20000 | L7: 20000 | N7: zeeshan account | O7: 50000 | W7: 2500 | X7: printer tonar | Y7: 45877 | Z7: zeeshan
C8: 2 | D8: haseeb hussain shah | E8: kamal | F8: south Africa | G8: 45877 | H8: kamal express | I8: appointment | J8: 23000 | K8: 15676 | L8: 15767 | N8: Kamal account | O8: 7324 | W8: 2000 | X8: water bill | Y8: 45969 | Z8: kamal
C9: 3 | D9: Muhammad Usman | E9: noman kazmi | F9: spain | G9: 45969 | H9: kamal express | I9: file | J9: 10000 | K9: 2300 ins | L9: 2300 ins | N9: Kamal account | O9: 7700 | P9: 5700 , 2000 zeeshan | W9: 7607 | X9: grocery | Y9: 45870 | Z9: zeeshan/kamal | AA9: 1350 paid kamal 6257 zeeshan
C10: 4 | D10: safia malik | E10: zeeshan | F10: austria | G10: 45999 | H10: kamal express | I10: appointment | J10: 35000 | K10: 14000 | L10: 14000 | N10: zeeshan account | O10: 21000 | W10: 17565 | X10: iseco bill | Y10: 26/08/2025 | Z10: zeeshan
C11: 5 | D11: Shahroze & Mishal | E11: zeeshan | F11: Thailand | H11: skyline holiday | I11: visa | J11: 40000 | K11: 29000 | L11: 11000 | N11: zeeshan account | W11: 500 | X11: hardwear | Y11: 45877 | Z11: kamal
C12: 6 | D12: ayesha khattak | E12: kamal | F12: turkey e visa | G12: 13/08/2025 | H12: kamal express | I12: visa | L12: S | N12: kamal account | W12: 1000 | X12: water bill | Y12: 15/08/2025 | Z12: zeeshan
C13: 7 | D13: Shahroze & Mishal | E13: zeeshan | F13: ticket | G13: 19/08/2025 | H13: saqib | I13: ticket | J13: 595000 | K13: 580000 | N13: zeeshan account | O13: 15000 | W13: 13493 | X13: lunch | Y13: 45870 | Z13: zeesan/kamal | AA13: 2130 paid kamal 11813 zeeshan
C14: 8
C15: 9
C16: 10
C17: 3
C18: 14
C39: 45753 | D39: 20000 | E39: zeeshan received | F39: from kamal ahmed
C40: 45814 | D40: 20000 | E40: kamal received | F40: from zeeshan siddique
C41: 16/06/2025 | D41: 43000 | E41: kamal received | F41: feom zeeshan account

Sheet SEP 2025 
E2: SEP 2025 SALE
W4: office expnses
C6: Serial number | D6: client name | E6: Care of | F6: country | G6: payment Date | H6: Vender | I6: services | J6: total amount | K6: Payable | L6: cost | M6: S/C | N6: status | O6: profit | P6: payable to company | Q6: account | W6: amount | X6: items | Y6: date | Z6: zeeshan / kamal
C7: 1 | D7: Usman Rasheed | E7: zeeshan | F7: Hungary | G7: 45756 | H7: shabeer bahi | I7: appointment | J7: 15000 | K7: 10000 | N7: payment received zeeshan ` | O7: 5000 | W7: 1600 | X7: water bill | Y7: 45666 | Z7: kamal
C8: 2 | D8: Nabia Farrah | E8: zeeshan | F8: Hungary | G8: 45847 | H8: kamal express | I8: appointment + visa file | J8: 70000 | K8: 15000 | N8: payment received zeeshan ` | O8: 25000 | W8: 11700 | X8: Grocery | Y8: 03/22/sep 2025 | Z8: zeeshan
D9: Muhammad Ramzan | E9: zeeshan | F9: Spain | G9: 45909 | H9: kamal express | I9: appointment | J9: 30000 | K9: 6000 | N9: payment received zeeshan ` | O9: 24000 | W9: 4860 | X9: Grocery | Y9: 45901 | Z9: Zeeshan
C10: 3 | D10: Muhammad Salman khan | E10: kamal | F10: France | G10: 45970 | H10: Awais | I10: appointment | J10: 200000 | K10: 85000 | N10: payment kamal account | O10: 115000 | P10: payment done kamal/zeeshan | W10: 18770 | X10: lunch | Y10: sep | Z10: zeeshan / kamal | AA10: 5340 paid kamal 13430 paid zeeshan
C11: 4 | D11: Nabia Farrah | E11: zeeshan | F11: Hungary | G11: 26/09/2025 | H11: saqib | I11: ticket | J11: 264000 | K11: 247000 | N11: payment zeeshan account | O11: 17000 | W11: 15270 | X11: ISECO | Y11: sep | Z11: zeeshan
C12: 5 | D12: Muhammad fayyaz +2 | E12: kamal | F12: Bulgaria | G12: 22/09/2025 | H12: naeem | I12: appointment | J12: 750000 | K12: 450000 | N12: payment received kamal | O12: 300000 | W12: 2000 | X12: chair repare | Y12: sep | Z12: zeeshan
C13: 6 | W13: 3300 | X13: washroom clean | Y13: sep | Z13: zeeshan
C14: 7 | W14: 8000 | X14: dinner f10 | Y14: sep | Z14: zeeshan
C15: 8 | W15: 3800 | X15: PTCL | Y15: 24/09/2025 | Z15: kamal
C16: 9
C17: 10
C18: 3
C19: 14
C40: 45753 | D40: 20000 | E40: zeeshan received | F40: from kamal ahmed
C41: 45814 | D41: 20000 | E41: kamal received | F41: from zeeshan siddique
C42: 16/06/2025 | D42: 43000 | E42: kamal received | F42: feom zeeshan account

Sheet OCT 2025
E2: OCT 2025 SALE
W4: office expnses
C6: Serial number | D6: client name | E6: Care of | F6: country | G6: payment Date | H6: Vender | I6: services | J6: total amount | K6: Payable | L6: cost | M6: S/C | N6: status | O6: profit | P6: payable to company | Q6: account | W6: amount | X6: items | Y6: date | Z6: zeeshan / kamal
C7: 1 | D7: Muhammad yasser | E7: kamal | F7: Hungary | H7: kamal express & holidays | I7: visa appointment | J7: 35000 | K7: 5000 | N7: payment received kamal bahi account | W7: 2600 | X7: water bill | Y7: 45910 | Z7: zeeshan
C8: 2 | D8: Asad Mehmood | E8: Zeeshan | F8: Hungary | G8: 45940 | H8: kamal express & holidays | I8: visa appointment | J8: 40000 | K8: 5000 | N8: payment received cash | W8: 3630 | X8: ptcl | Y8: 17/10/2025 | Z8: kamal
C9: 3 | D9: Rasoolan bibi | E9: Zeeshan | F9: France | G9: 14/10/2025 | H9: Awais | I9: visa appointment | J9: 110000 | K9: 80000 | N9: Payment received zeeshan ubl | O9: 60k profit 20k tra kamal bahi | W9: 14940 | X9: iseco | Y9: 27/10/2025 | Z9: zeeshan
C10: 4 | D10: Jamshid Ali | E10: Zeeshan | F10: France | G10: 14/10/2025 | H10: Awais | I10: visa appointment | J10: 110000 | K10: 80000 | N10: Payment received zeeshan ubl | W10: 9835 | X10: Grocery | Y10: 45931 | Z10: zeeshan
C11: 5 | D11: Muhammad Hamza | E11: Zeeshan | F11: japan | G11: 16/10/2025 | H11: kamal express & holidays | I11: ticket booking | J11: 2000 | K11: 0 | N11: Payment received zeeshan faysal bank | W11: 5200 | X11: electronic catel | Y11: 30/10/2025 | Z11: kamal
C12: 6 | D12: asif ali | E12: zeeshan | F12: german | G12: 28/10/2025 | H12: kamal express & holidays | I12: visa file | J12: 30000 | K12: 4000 | N12: Payment received zeeshan faysal bank | O12: 20k pay kamal bahi 26 oct | W12: 16260 | X12: Lunch | Y12: 45931 | Z12: zeeshan
C13: 7 | D13: Muhammad hafeez | E13: Zeeshan | F13: german | G13: 28/10/2025 | H13: kamal express & holidays | I13: visa file | J13: 30000 | K13: 4000 | N13: Payment received zeeshan faysal bank | W13: 4140 | X13: extra item | Y13: 45931 | Z13: zeeshan
C14: 8 | D14: Umar farooq | E14: Zeeshan | F14: poland | G14: 27/10/2025 | H14: shabber | I14: visa appointment | J14: 30000 | K14: 5000 | N14: payment receuved zeeshan faysal bank | O14: 25000
C15: 9 | D15: Abdul sammad khan | E15: kamal | F15: france | G15: 29/10/2025 | H15: awais | I15: visa appointment | J15: 140000 | K15: 80000 | N15: payment received kamal bahi account | O15: 30k pay zeeshan
C16: 10 | D16: Nabia farrah | E16: Zeeshan | F16: Hungary | G16: 31/10/2025 | H16: saqib | I16: ticket date change | J16: 153223 | K16: 145223 | N16: payment received zeeshan ubl | O16: 8000
C17: 3 | D17: Nabia farrah | E17: Zeeshan | F17: Hungary | G17: 31/10/2025 | H17: kamal express & holidays | I17: hotel charges | J17: 21000 | K17: 0 | N17: payment received zeeshan ubl | O17: 21000
C18: 14
C39: 45753 | D39: 20000 | E39: zeeshan received | F39: from kamal ahmed
C40: 45814 | D40: 20000 | E40: kamal received | F40: from zeeshan siddique
C41: 16/06/2025 | D41: 43000 | E41: kamal received | F41: feom zeeshan account

Sheet NOV 2025
E2: NOV 2025 SALE
W4: office expnses
C6: Serial number | D6: client name | E6: Care of | F6: country | G6: payment Date | H6: Vender | I6: services | J6: total amount | K6: Payable | L6: cost | M6: S/C | N6: status | O6: profit | P6: payable to company | Q6: account | W6: amount | X6: items | Y6: date | Z6: zeeshan / kamal
C7: 1 | D7: Asad Mahmood | E7: zeeshan | F7: Hungary | G7: 45849 | H7: kamal express | I7: visa appointment | J7: 35000 | K7: 7500 | N7: payment received zeeshan faysal bank | P7: 12k pay kamal sir 08/nov | W7: 2200 | X7: water bill | Y7: 45941 | Z7: zeeshan
C8: 2 | D8: Usman Rasheed | E8: zeeshan | F8: Serbia | G8: 13/11/2025 | H8: Asif | I8: Serbia work visa | J8: 165000 | N8: Payment received zeeshan cash | W8: 10130 | X8: iseco bill | Y8: 24/11/2025 | Z8: zeeshan
C9: 3 | D9: M jahanger mazhar | E9: zeeshan | F9: Hungary | G9: 14/11/2025 | H9: kamal express | I9: visa appointment | J9: 22000 | K9: 4000 | N9: payment received zeeshan faysal bank | O9: 18000 | W9: 5970 | X9: Grocery | Y9: 45962 | Z9: Zeeshan
C10: 4 | D10: usman fazil | E10: kamal | F10: Singapore | G10: 28/11/2025 | H10: karachi | I10: visit visa | J10: 18000 | K10: 14000 | N10: payment received kamal account | W10: 17320 | X10: Lunch | Y10: 45962 | Z10: zeeshan/Kamal | AA10: 1800 Kamal sir / 15520 zeeshan
C11: 5 | D11: khwaja haider farooq | E11: kamal | F11: Singapore | G11: 28/11/2025 | H11: karachi | I11: visit visa | J11: 18000 | K11: 14000 | N11: payment received kamal account
C12: 6
C13: 7
C14: 8
C15: 9
C16: 10
C17: 3
C18: 14
C39: 45753 | D39: 20000 | E39: zeeshan received | F39: from kamal ahmed
C40: 45814 | D40: 20000 | E40: kamal received | F40: from zeeshan siddique
C41: 16/06/2025 | D41: 43000 | E41: kamal received | F41: feom zeeshan account

Sheet DEC 2025 
E2: DEC 2025 SALE
W4: office expnses
C6: Serial number | D6: client name | E6: Care of | F6: country | G6: payment Date | H6: Vender | I6: services | J6: total amount | K6: Payable | L6: cost | M6: S/C | N6: status | O6: profit | P6: payable to company | Q6: account | W6: amount | X6: items | Y6: date | Z6: zeeshan / kamal
C7: 1 | D7: Marrij Mushtaq | E7: zeeshan | F7: Malaysia | G7: 45700 | H7: saqib (HMN HOLIDAYS) | I7: Ticket | J7: 92000 | K7: 84300 | N7: paid saqib dated 03/12/2025 | O7: 7700 | P7: 7700 | W7: 4090 | X7: ptcl | Y7: 20/12/2025 | Z7: kamal
C8: 2 | D8: Muhammad Umar Maqsood | E8: zeeshan | F8: Poland | G8: 45759 | H8: Shabber | I8: appointment | J8: 25000 | K8: 5000 | N8: Paid sabber dated 04/12/2025 | O8: 20000 | W8: 1600 | X8: Water | Y8: 45992 | Z8: zeeshan
C9: 3 | D9: Raja ayaz khalid | E9: zeeshan | F9: Bulgaria | G9: 09/12/20255 | I9: appointment | J9: 275000 | K9: 150000 | W9: 1950 | X9: grocery | Y9: 45992 | Z9: zeeshan
D10: Salma bibi | E10: zeeshan | F10: france | G10: remaning | H10: Awais | I10: appointment | J10: 100000 | K10: 80000 | N10: payment remaning shabber | O10: 20000 | W10: 8760 | X10: Lunch | Y10: 45992 | Z10: zeeshan/kamal | AA10: 8380 zeeshan / 380 kamal sir
C11: 4 | D11: Tayyab aslam | E11: zeeshan | F11: Dubai | G11: 46000 | H11: ahsan latif | I11: appointment | J11: 30000 | K11: 22000 | N11: Paid ahsan latif 09/12/2025 | O11: 8000
C12: 5 | D12: jahangir docuuments | E12: kamal | F12: UAE | G12: 46003 | H12: Sajjad diplomatic | I12: attestation | J12: 66000 | K12: 63000 | N12: paid sajjad dated 12/12/2025 | O12: 3000
C13: 6 | D13: shakir & kainat | E13: kamal | F13: Indonesia | G13: 16/12/2025 | H13: wasif | I13: visa | J13: 58000 | K13: 42000 | N13: paid kamal bahi 18/12/2025 | O13: 16000
C14: 7 | D14: awais iqbal khan | E14: zeeshan | F14: Malaysia | H14: wasif | I14: visa | J14: 15500 | K14: 15500 | N14: paid kamal bahi 18/12/2025 | O14: 0
C15: 8 | D15: syed mahmood hussain | E15: kamal | F15: ethopia | G15: 17/12/2025 | H15: kamal express | I15: visa
C16: 9 | D16: Awais/ anita | E16: zeeshan | F16: indonesia/malaysia | H16: wasif | I16: visa | J16: 53000 | K16: 425000 | N16: paid wasif | O16: 10500
C17: 10 | D17: Rozi / shumail | E17: zeeshan | F17: baku/indonesia | H17: wasif/kamal express | I17: visa | J17: 96000 | K17: 74000 | N17: paid wasif / kamal express | O17: 22000 | P17: 10,000 Paid kamal bahi
C18: 3 | D18: Asra Hameed | E18: zeeshan | F18: Dubai | G18: 22/12/2025 | H18: Humais bahi | I18: appointment | J18: 70000 | K18: 45000 | N18: Paid to humais bahi 31/12/2025 | O18: 250000 | P18: 17500 paid tayyab salary
C19: 14 | D19: Nadia zafar | E19: zeeshan | F19: schengen | G19: 19/12/2025 | H19: Abu bakar/aqib | I19: translation and appostile | J19: 18500 | K19: 13500 | N19: paid aqib and abu bakar | O19: 5000
C40: 45753 | D40: 20000 | E40: zeeshan received | F40: from kamal ahmed
C41: 45814 | D41: 20000 | E41: kamal received | F41: from zeeshan siddique
C42: 16/06/2025 | D42: 43000 | E42: kamal received | F42: feom zeeshan account

Sheet Sheet1
D15: Column | E15: Header | F15: Type / Format | G15: Description / Example
D16: **A** | E16: `Transaction Date` | F16: Date (`YYYY-MM-DD`) | G16: Date invoice or service initiated
D17: **B** | E17: `Serial No.` | F17: Number / ID | G17: Unique job identifier (`1`, `2`, `3`...)
D18: **C** | E18: `Client Name` | F18: Plain Text | G18: e.g., `Usman`, `Hussain Ali Hashmi`
D19: **D** | E19: `Care Of (Agent)` | F19: Dropdown | G19: `Zeeshan`, `Kamal`, etc.
D20: **E** | E20: `Country` | F20: Plain Text | G20: `Germany`, `Singapore`, `Belgium`
D21: **F** | E21: `Service` | F21: Dropdown / Text | G21: `Profile`, `Visa`, `Work Visa Appointment`
D22: **G** | E22: `Vendor` | F22: Plain Text | G22: `Nawander`, `Fakhar`, `Nomi`, `Adamjee`
D23: **H** | E23: `Total Invoiced (PKR)` | F23: Currency / Number | G23: Total price agreed with client
D24: **I** | E24: `Received Amount (PKR)` | F24: Currency / Number | G24: Actual cash/bank received from client
D25: **J** | E25: `Receivable Balance` | F25: Formula | G25: `=H2-I2`
D26: **K** | E26: `Vendor Cost / Payable` | F26: Currency / Number | G26: Amount payable to vendor
... D28: **M** | E28: `Gross Profit (PKR)` | F28: Formula | G28: `=I2-K2`
